fasjson/__init__.py
fasjson/lib/__init__.py
fasjson/lib/ldap/__init__.py
fasjson/lib/ldap/client.py
fasjson/lib/ldap/converters.py
fasjson/lib/ldap/models.py
fasjson/web/__init__.py
fasjson/web/apis/__init__.py
fasjson/web/apis/base.py
fasjson/web/apis/errors.py
fasjson/web/apis/v1.py
fasjson/web/app.py
fasjson/web/base_routes.py
fasjson/web/defaults.cfg
fasjson/web/extensions/__init__.py
fasjson/web/extensions/flask_ipacfg.py
fasjson/web/resources/__init__.py
fasjson/web/resources/base.py
fasjson/web/resources/certs.py
fasjson/web/resources/groups.py
fasjson/web/resources/me.py
fasjson/web/resources/search.py
fasjson/web/resources/users.py
fasjson/web/utils/__init__.py
fasjson/web/utils/ipa.py
fasjson/web/utils/pagination.py
fasjson/web/utils/request_parsing.py
fasjson-1.7.0.dist-info/METADATA
fasjson-1.7.0.dist-info/WHEEL
fasjson-1.7.0.dist-info/licenses/COPYING
fasjson-1.7.0.dist-info/RECORD
